hal9k/__init__.py
hal9k/const.py
hal9k/meta.py
hal9k/track.py
Lib_HaL9k-0.7.0.dist-info/LICENSE
Lib_HaL9k-0.7.0.dist-info/METADATA
Lib_HaL9k-0.7.0.dist-info/WHEEL
Lib_HaL9k-0.7.0.dist-info/top_level.txt
Lib_HaL9k-0.7.0.dist-info/RECORD
