Metadata-Version: 2.1
Name: Lib-HaL9k
Version: 0.7.0
Summary: The HackerLab 9000 Controller Library.
Home-page: https://github.com/haxys-labs/Lib-Hal9k
Author: CMSteffen
Author-email: cmsteffen@haxys.net
License: MIT
Project-URL: Source Code, https://github.com/haxys-labs/Lib-Hal9k
Project-URL: Documentation, https://github.com/haxys-labs/Lib-Hal9k
Keywords: hacker hacking lab laboratory virtual machine virtualbox vm
Platform: UNKNOWN
Classifier: Development Status :: 2 - Pre-Alpha
Classifier: Intended Audience :: Developers
Classifier: License :: OSI Approved :: MIT License
Classifier: Programming Language :: Python :: 3
Classifier: Programming Language :: Python :: 3.6
Classifier: Programming Language :: Python :: 3.7
Classifier: Programming Language :: Python :: 3.8
Classifier: Topic :: Software Development :: Libraries
Requires-Dist: virtualbox (==2.0.0)
